robotframework_docgen/__init__.py
robotframework_docgen/cli.py
robotframework_docgen/dashboard.py
robotframework_docgen/errors.py
robotframework_docgen/generator.py
robotframework_docgen/parser.py
robotframework_docgen/templates/dashboard.html
robotframework_docgen/templates/libdoc.html
robotframework_libdocgen-2.1.1.dist-info/licenses/LICENSE
robotframework_libdocgen-2.1.1.dist-info/METADATA
robotframework_libdocgen-2.1.1.dist-info/WHEEL
robotframework_libdocgen-2.1.1.dist-info/entry_points.txt
robotframework_libdocgen-2.1.1.dist-info/top_level.txt
robotframework_libdocgen-2.1.1.dist-info/RECORD
