Metadata-Version: 2.4
Name: robotframework-libdocgen
Version: 2.1.1
Summary: A powerful documentation generator for Robot Framework libraries that creates professional HTML and Markdown documentation
Author-email: Deekshith Poojary <deekshithpoojary355@gmail.com>
License: Apache-2.0
Project-URL: Homepage, https://github.com/deekshith-poojary98/robotframework-docgen
Project-URL: Documentation, https://github.com/deekshith-poojary98/robotframework-docgen#readme
Project-URL: Repository, https://github.com/deekshith-poojary98/robotframework-docgen
Project-URL: Issues, https://github.com/deekshith-poojary98/robotframework-docgen/issues
Keywords: robotframework,documentation,generator,html,markdown,cli
Classifier: Development Status :: 4 - Beta
Classifier: Intended Audience :: Developers
Classifier: License :: OSI Approved :: Apache Software License
Classifier: Programming Language :: Python :: 3.8
Classifier: Programming Language :: Python :: 3.9
Classifier: Programming Language :: Python :: 3.10
Classifier: Programming Language :: Python :: 3.11
Classifier: Programming Language :: Python :: 3.12
Classifier: Programming Language :: Python :: 3.13
Classifier: Programming Language :: Python :: 3.14
Classifier: Topic :: Software Development :: Documentation
Classifier: Topic :: Software Development :: Libraries :: Python Modules
Classifier: Framework :: Robot Framework
Requires-Python: >=3.8
License-File: LICENSE
Requires-Dist: robotframework>=5.0.1
Requires-Dist: markdown>=3.4.0
Requires-Dist: pygments>=2.10.0
Requires-Dist: rich>=13.0.0
Provides-Extra: dev
Requires-Dist: pytest>=7.0.0; extra == "dev"
Requires-Dist: black>=22.0.0; extra == "dev"
Requires-Dist: flake8>=4.0.0; extra == "dev"
Dynamic: license-file
